krsh/__init__.py
krsh/cmd/__init__.py
krsh/cmd/cli.py
krsh/cmd/cmd_apply.py
krsh/cmd/cmd_configure.py
krsh/cmd/cmd_plan.py
krsh/cmd/io.py
krsh/cmd/plan.py
krsh/cmd/utils.py
krsh/cmd/group_create/__init__.py
krsh/cmd/group_create/cmd_component.py
krsh/cmd/group_create/cmd_pipeline.py
krsh/cmd/group_create/cmd_project.py
krsh/cmd/group_create/templates/component/__init__.py
krsh/cmd/group_create/templates/component/component.py
krsh/cmd/group_create/templates/pipeline/pipeline.py
krsh/config/__init__.py
krsh/config/config.py
krsh/kubeflow/__init__.py
krsh/kubeflow/client.py
krsh/kubeflow/pipeline.py
tests/__init__.py
tests/cmd/__init__.py
tests/cmd/test_cmd_apply.py
tests/cmd/test_cmd_configure.py
tests/cmd/test_cmd_plan.py
tests/cmd/create/__init__.py
tests/cmd/create/test_create_component.py
tests/cmd/create/test_create_pipeline.py
tests/cmd/create/test_create_project.py
tests/kubeflow/__init__.py
tests/kubeflow/test_client.py
tests/kubeflow/test_pipeline.py
krsh-1.0.0a0.dist-info/AUTHORS
krsh-1.0.0a0.dist-info/LICENSE
krsh-1.0.0a0.dist-info/METADATA
krsh-1.0.0a0.dist-info/WHEEL
krsh-1.0.0a0.dist-info/entry_points.txt
krsh-1.0.0a0.dist-info/top_level.txt
krsh-1.0.0a0.dist-info/RECORD
