Metadata-Version: 2.1
Name: krsh
Version: 1.0.0a0
Summary: UNKNOWN
Home-page: https://github.com/riiid/krsh
Author: AIOps Squad, Riiid Inc
License: UNKNOWN
Download-URL: https://github.com/riiid/krsh/archive/master.zip
Keywords: kubeflow,krsh,krsh
Platform: UNKNOWN
Classifier: Programming Language :: Python :: 3
Requires-Python: >=3.7
License-File: LICENSE
License-File: AUTHORS
